[
  {
    "link": "https://cdn.discordapp.com/attachments/1270459402381426809/1518286458786676756/VID_20260621_160726.mp4?ex=6a395df4&is=6a380c74&hm=fc7cd6ecf1158d83a2a1eb72f8ed9c21b5ccd0c6e5fcf183e5b2b4224ca89053&",
    "user": {
      "id": "413750550866165771",
      "username": "hejteriownerstjepan",
      "tag": "hejteriownerstjepan"
    },
    "createdAt": "2026-06-21T16:08:20.841Z"
  },
  {
    "link": "https://cdn.discordapp.com/attachments/1270459402381426809/1502964795975143454/Screenrecorder-2026-05-09-22-52-17-330.mp4?ex=6a01a08b&is=6a004f0b&hm=eea203e7419d1483c4781953774d03de131b24e8bd1befdf0d9f437a4df00725&",
    "user": {
      "id": "413750550866165771",
      "username": "hejteriownerstjepan",
      "tag": "hejteriownerstjepan"
    },
    "channel": {
      "id": "1270459402381426809",
      "name": "🎥｜videos"
    },
    "message": {
      "id": "1502964796084191496",
      "content": "",
      "createdAt": "2026-05-10T09:25:31.122Z"
    }
  },
  {
    "link": "https://cdn.discordapp.com/attachments/1270459402381426809/1502739142868734002/2026-05-09-201344034.mp4?ex=6a00ce63&is=69ff7ce3&hm=cfdea901fce930a25f9463b9e9eeeeccc339801bd60e69db1d43a05efff17409&",
    "user": {
      "id": "1313987476855066756",
      "username": "ciaomond",
      "tag": "ciaomond"
    },
    "channel": {
      "id": "1270459402381426809",
      "name": "🎥｜videos"
    },
    "message": {
      "id": "1502739143610863828",
      "content": "<a:emoji_81:1497711547303198761>",
      "createdAt": "2026-05-09T18:28:51.380Z"
    }
  }
]